genni/__init__.py
genni/data_getters.py
genni/experiment.py
genni/griding/__init__.py
genni/griding/get_grid.py
genni/griding/interpolation.py
genni/griding/stats_plotting.py
genni/nets/Nets.py
genni/nets/__init__.py
genni/save_load.py
genni/training.py
genni/training_utils.py
genni/utils.py
genni-1.0.3.dist-info/LICENSE
genni-1.0.3.dist-info/WHEEL
genni-1.0.3.dist-info/METADATA
genni-1.0.3.dist-info/RECORD
