Metadata-Version: 2.1
Name: genni
Version: 1.0.3
Summary: GENNI: Visualising the Geometry of Equivalences for Neural Network Identifiability
Home-page: https://github.com/Do-Not-Circulate/GENNI_public
License: MIT
Keywords: ml,visualisation,neural-networks,diffgeom,pytorch
Author: Arinbjörn Kolbeinsson
Maintainer: Isak Falk
Maintainer-email: ucabitf@ucl.ac.uk
Requires-Python: >=3.8,<3.9
Classifier: License :: OSI Approved :: MIT License
Classifier: Operating System :: OS Independent
Classifier: Programming Language :: Python :: 3
Classifier: Programming Language :: Python :: 3.8
Requires-Dist: matplotlib (>=3.3.2,<4.0.0)
Requires-Dist: numpy (>=1.19.4,<2.0.0)
Requires-Dist: pandas (>=1.1.4,<2.0.0)
Requires-Dist: plotly (>=4.12.0,<5.0.0)
Requires-Dist: pyyaml (>=5.3.1,<6.0.0)
Requires-Dist: ray[tune] (>=1.0.0,<2.0.0)
Requires-Dist: seaborn (>=0.11.0,<0.12.0)
Requires-Dist: tensorboard (>=2.3.0,<3.0.0)
Requires-Dist: torch (>=1.7.0,<2.0.0)
Requires-Dist: torchvision (>=0.8.1,<0.9.0)
Requires-Dist: tqdm (>=4.51.0,<5.0.0)
Requires-Dist: umap_learn (>=0.4.6,<0.5.0)
Project-URL: Repository, https://github.com/Do-Not-Circulate/GENNI_public
